iflow_mcp_ipospelov_mcp_memory_bank/__init__.py
iflow_mcp_ipospelov_mcp_memory_bank/__main__.py
iflow_mcp_ipospelov_mcp_memory_bank/main.py
iflow_mcp_ipospelov_mcp_memory_bank/guides/__init__.py
iflow_mcp_ipospelov_mcp_memory_bank/guides/benefits.py
iflow_mcp_ipospelov_mcp_memory_bank/guides/setup.py
iflow_mcp_ipospelov_mcp_memory_bank/guides/structure.py
iflow_mcp_ipospelov_mcp_memory_bank/guides/usage.py
iflow_mcp_ipospelov_mcp_memory_bank/templates/__init__.py
iflow_mcp_ipospelov_mcp_memory_bank/templates/active_context.py
iflow_mcp_ipospelov_mcp_memory_bank/templates/memory_bank_instructions.py
iflow_mcp_ipospelov_mcp_memory_bank/templates/product_context.py
iflow_mcp_ipospelov_mcp_memory_bank/templates/progress.py
iflow_mcp_ipospelov_mcp_memory_bank/templates/projectbrief.py
iflow_mcp_ipospelov_mcp_memory_bank/templates/system_patterns.py
iflow_mcp_ipospelov_mcp_memory_bank/templates/tech_context.py
iflow_mcp_ipospelov_mcp_memory_bank-0.1.0.dist-info/licenses/LICENSE
iflow_mcp_ipospelov_mcp_memory_bank-0.1.0.dist-info/METADATA
iflow_mcp_ipospelov_mcp_memory_bank-0.1.0.dist-info/WHEEL
iflow_mcp_ipospelov_mcp_memory_bank-0.1.0.dist-info/entry_points.txt
iflow_mcp_ipospelov_mcp_memory_bank-0.1.0.dist-info/top_level.txt
iflow_mcp_ipospelov_mcp_memory_bank-0.1.0.dist-info/RECORD
