Metadata-Version: 2.4
Name: iflow-mcp_ipospelov_mcp-memory-bank
Version: 0.1.0
Summary: Memory Bank helper for AI assistant
Classifier: Programming Language :: Python :: 3
Requires-Python: >=3.10
License-File: LICENSE
Requires-Dist: mcp
Provides-Extra: server
Requires-Dist: httpx; extra == "server"
Requires-Dist: uvicorn; extra == "server"
Requires-Dist: starlette; extra == "server"
Provides-Extra: all
Requires-Dist: httpx; extra == "all"
Requires-Dist: uvicorn; extra == "all"
Requires-Dist: starlette; extra == "all"
Dynamic: license-file
